muffin_redis_cache.py
muffin_redis_cache-0.2.2.dist-info/DESCRIPTION.rst
muffin_redis_cache-0.2.2.dist-info/METADATA
muffin_redis_cache-0.2.2.dist-info/metadata.json
muffin_redis_cache-0.2.2.dist-info/RECORD
muffin_redis_cache-0.2.2.dist-info/top_level.txt
muffin_redis_cache-0.2.2.dist-info/WHEEL
