Metadata-Version: 2.0
Name: muffin-redis-cache
Version: 0.2.2
Summary: UNKNOWN
Home-page: https://github.com/klinkin/muffin-redis-cache
Author: Mike Klimin
Author-email: klinkin@gmail.com
License: MIT
Keywords: asyncio,aiohttp,muffin,redis,cache
Platform: Any
Classifier: Development Status :: 4 - Beta
Classifier: Intended Audience :: Developers
Classifier: License :: OSI Approved :: BSD License
Classifier: Natural Language :: English
Classifier: Natural Language :: Russian
Classifier: Operating System :: OS Independent
Classifier: Programming Language :: Python :: 3
Classifier: Programming Language :: Python
Classifier: Topic :: Software Development :: Libraries :: Python Modules
Classifier: Topic :: Software Development :: Testing
Classifier: Topic :: Utilities
Requires-Dist: jsonpickle
Requires-Dist: muffin (>=0.0.99)
Requires-Dist: muffin-redis (>=0.0.6)
